nbg_currency_api/__init__.py
nbg_currency_api/api.py
nbg_currency_api/constants.py
nbg_currency_api/exceptions.py
nbg_currency_api/services.py
nbg_currency_api/types.py
tests/__init__.py
tests/conftest.py
tests/mocker.py
tests/async/__init__.py
tests/async/test_api.py
tests/async/test_services.py
tests/sync/__init__.py
tests/sync/test_api.py
tests/sync/test_services.py
nbg_currencies_api-0.1.4.dist-info/LICENSE
nbg_currencies_api-0.1.4.dist-info/METADATA
nbg_currencies_api-0.1.4.dist-info/WHEEL
nbg_currencies_api-0.1.4.dist-info/top_level.txt
nbg_currencies_api-0.1.4.dist-info/RECORD
