Metadata-Version: 2.2
Name: nbg-currencies-api
Version: 0.1.4
Summary: A Python wrapper over NBG official exchange rate of LARI against foreign currencies
Author: Illia Stebelskyi
Author-email: Illia Stebelskyi <illia.stebelski@gmail.com>
License: MIT License
Project-URL: Home, https://github.com/zelnkup/nbg-currencies-api
Keywords: nbg,currencies,api,exchange rates
License-File: LICENSE
Requires-Dist: requests
Provides-Extra: async
Requires-Dist: aiohttp; extra == "async"
Provides-Extra: dev
Requires-Dist: pytest; extra == "dev"
Requires-Dist: pytest-asyncio; extra == "dev"
Requires-Dist: pytest-cov; extra == "dev"
Dynamic: author
